ula.vhd
library IEEE;
use IEEE.std_logic_1164.all;
use IEEE.numeric_std.all;

entity ULA is
    port (
        entrada_A : in unsigned(15 downto 0);
        entrada_B : in unsigned(15 downto 0);
        selec_op : in unsigned(1 downto 0);
        resultado : out unsigned(15 downto 0);
        flag_zero : out std_logic;
        flag_neg : out std_logic;
        flag_carry : out std_logic
    );
end entity ULA;

architecture behavior of ULA is
    signal resultado_temp : unsigned(15 downto 0) := (others => '0');
    signal carry_temp : std_logic := '0';
    signal soma_temp : unsigned(16 downto 0);  -- Um bit extra para o carry
begin
    -- Cálculo da operação com possível carry
    soma_temp <= ('0' & entrada_A) + ('0' & entrada_B) when selec_op = "00" else
                 ('0' & entrada_A) - ('0' & entrada_B) when selec_op = "01" else
                 ('0' & (entrada_A or entrada_B)) when selec_op = "10" else  -- Operação OR
                 (others => '0');

    -- Atribuição do resultado
    resultado_temp <= soma_temp(15 downto 0);
    
    -- Flag de carry (bit 16 da soma/subtração)
    carry_temp <= soma_temp(16) when selec_op = "00" else  -- Carry para soma
                  not soma_temp(16) when selec_op = "01" else  -- Carry para subtração (invertido)
                  '0';  -- Outras operações não geram carry

    -- Sinais de saída
    resultado <= resultado_temp;
    flag_zero <= '1' when resultado_temp = 0 else '0';
    flag_neg <= resultado_temp(15);
    flag_carry <= carry_temp;
end architecture behavior;

accumulator.vhd
library IEEE;
use IEEE.std_logic_1164.all;
use IEEE.numeric_std.all;

entity accumulator is
    port(
        clk, rst, wr_en: in std_logic;
        data_in: in unsigned(15 downto 0);
        data_out: out unsigned(15 downto 0)
    );
end entity accumulator;

architecture a_accumulator of accumulator is

    signal data: unsigned(15 downto 0);

    begin

        process(clk, rst, wr_en)
        begin
            if rst = '1' then
                data <= "0000000000000000";
            elsif wr_en = '1' then
                if rising_edge(clk) then
                    data <= data_in;
                end if;
            end if;
        end process;

        data_out <= data;

end architecture a_accumulator;

reg16bits.vhd
library ieee;
use ieee.std_logic_1164.all;
use ieee.numeric_std.all;

entity reg16bits is
   port( clk      : in std_logic;
         rst      : in std_logic;
         wr_en    : in std_logic;
         data_in  : in unsigned(15 downto 0);
         data_out : out unsigned(15 downto 0)
   );
end entity;

architecture a_reg16bits of reg16bits is
   signal registro: unsigned(15 downto 0);
begin
   process(clk,rst,wr_en)  -- acionado se houver mudança em clk, rst ou wr_en
   begin
      if rst='1' then
         registro <= "0000000000000000";
      elsif wr_en='1' then
         if rising_edge(clk) then
            registro <= data_in;
         end if;
      end if;
   end process;

   data_out <= registro;  -- conexao direta, fora do processo
end architecture;

register_bank.vhd
library ieee;
use ieee.std_logic_1164.all;
use ieee.numeric_std.all;

entity register_bank is
    port(
        data_in   : in unsigned(15 downto 0);
        clk       : in std_logic;
        wr_en     : in std_logic;
        reg_code  : in unsigned(2 downto 0);
        rst       : in std_logic;
        data_out  : out unsigned(15 downto 0)
    );
end entity register_bank;

architecture a_register_bank of register_bank is
  component reg16bits is
    port (
        clk      : in std_logic;
        rst      : in std_logic;
        wr_en    : in std_logic;
        data_in  : in unsigned(15 downto 0);
        data_out : out unsigned(15 downto 0)
    );
  end component;

  signal data_out_0_s,data_out_1_s,data_out_2_s : unsigned(15 downto 0) := (others => '0');
  signal data_out_3_s,data_out_4_s,data_out_5_s : unsigned(15 downto 0) := (others => '0');

  signal wr_en_0_s,wr_en_1_s,wr_en_2_s : std_logic := '0';
  signal wr_en_3_s,wr_en_4_s,wr_en_5_s : std_logic := '0';

  begin

    --WRITE ENABLE
    wr_en_0_s <= '1' when wr_en = '1' and reg_code = "000" else '0';
    wr_en_1_s <= '1' when wr_en = '1' and reg_code = "001" else '0';
    wr_en_2_s <= '1' when wr_en = '1' and reg_code = "010" else '0';
    wr_en_3_s <= '1' when wr_en = '1' and reg_code = "011" else '0';
    wr_en_4_s <= '1' when wr_en = '1' and reg_code = "100" else '0';
    wr_en_5_s <= '1' when wr_en = '1' and reg_code = "101" else '0';


    --REGISTER DEFINITION
    reg0: reg16bits port map(clk,rst,wr_en_0_s,data_in,data_out_0_s);
    reg1: reg16bits port map(clk,rst,wr_en_1_s,data_in,data_out_1_s);
    reg2: reg16bits port map(clk,rst,wr_en_2_s,data_in,data_out_2_s);
    reg3: reg16bits port map(clk,rst,wr_en_3_s,data_in,data_out_3_s);
    reg4: reg16bits port map(clk,rst,wr_en_4_s,data_in,data_out_4_s);
    reg5: reg16bits port map(clk,rst,wr_en_5_s,data_in,data_out_5_s);

    data_out <= data_out_0_s when reg_code = "000" else
                data_out_1_s when reg_code = "001" else
                data_out_2_s when reg_code = "010" else
                data_out_3_s when reg_code = "011" else
                data_out_4_s when reg_code = "100" else
                data_out_5_s when reg_code = "101" else
                "0000000000000000";

end architecture a_register_bank;

ULA_ACC_BANK/ula_acc_bank.vhd
library IEEE;
use IEEE.std_logic_1164.all;
use IEEE.numeric_std.all;

entity ula_acc_bank is
    port (
        -- Global control signals
        clk         : in std_logic;
        rst         : in std_logic;
        
        -- Register bank control
        bank_wr_en  : in std_logic;
        reg_code    : in unsigned(2 downto 0);
        bank_data_in : in unsigned(15 downto 0);
        
        -- Accumulator control
        acc_wr_en   : in std_logic;
        
        -- ula control
        selec_op    : in unsigned(1 downto 0);
        
        -- ula outputs
        result      : out unsigned(15 downto 0);
        flag_zero   : out std_logic;
        flag_neg    : out std_logic;
        flag_carry  : out std_logic
    );
end entity ula_acc_bank;

architecture a_ula_acc_bank of ula_acc_bank is
    -- Register bank component
    component register_bank is
        port(
            data_in   : in unsigned(15 downto 0);
            clk       : in std_logic;
            wr_en     : in std_logic;
            reg_code  : in unsigned(2 downto 0);
            rst       : in std_logic;
            data_out  : out unsigned(15 downto 0)
        );
    end component;

    -- ula component (use lowercase consistently)
    component ula is
        port (
            entrada_A : in unsigned(15 downto 0);
            entrada_B : in unsigned(15 downto 0);
            selec_op  : in unsigned(1 downto 0);
            resultado : out unsigned(15 downto 0);
            flag_zero : out std_logic;
            flag_neg  : out std_logic;
            flag_carry : out std_logic
        );
    end component;

    -- Accumulator component
    component accumulator is
        port(
            clk, rst, wr_en: in std_logic;
            data_in: in unsigned(15 downto 0);
            data_out: out unsigned(15 downto 0)
        );
    end component;

    -- Internal connection signals
    signal bank_data_out : unsigned(15 downto 0);
    signal acc_data_out  : unsigned(15 downto 0);
    signal ula_result    : unsigned(15 downto 0);

begin
    -- Register bank instance
    bank: register_bank port map(
        data_in  => bank_data_in,
        clk      => clk,
        wr_en    => bank_wr_en,
        reg_code => reg_code,
        rst      => rst,
        data_out => bank_data_out
    );
    
    -- Accumulator instance
    acc: accumulator port map(
        clk      => clk,
        rst      => rst,
        wr_en    => acc_wr_en,
        data_in  => ula_result,
        data_out => acc_data_out
    );
    
    -- ula instance (use lowercase to match component declaration)
    ula_comp: ula port map(
        entrada_A => acc_data_out,   -- Accumulator as first ula input
        entrada_B => bank_data_out,  -- Register bank as second ula input
        selec_op  => selec_op,
        resultado => ula_result,
        flag_zero => flag_zero,
        flag_neg  => flag_neg,
        flag_carry => flag_carry
    );
    
    -- Connect ula result to module output
    result <= ula_result;

end architecture a_ula_acc_bank;

ula_acc_bank_tb.vhd
library IEEE;
use IEEE.std_logic_1164.all;
use IEEE.numeric_std.all;

entity ula_acc_bank_tb is
end entity;

architecture a_ula_acc_bank_tb of ula_acc_bank_tb is
    -- Component declaration for the unit under test (UUT)
    component ula_acc_bank is
        port (
            clk         : in std_logic;
            rst         : in std_logic;
            bank_wr_en  : in std_logic;
            reg_code    : in unsigned(2 downto 0);
            bank_data_in : in unsigned(15 downto 0);
            acc_wr_en   : in std_logic;
            selec_op    : in unsigned(1 downto 0);
            result      : out unsigned(15 downto 0);
            flag_zero   : out std_logic;
            flag_neg    : out std_logic;
            flag_carry  : out std_logic
        );
    end component;

    -- Clock period definition
    constant clk_period : time := 100 ns;
    
    -- Stimuli signals
    signal clk         : std_logic := '0';
    signal rst         : std_logic := '1';  -- Initial reset
    signal bank_wr_en  : std_logic := '0';
    signal reg_code    : unsigned(2 downto 0) := "000";
    signal bank_data_in : unsigned(15 downto 0) := (others => '0');
    signal acc_wr_en   : std_logic := '0';
    signal selec_op    : unsigned(1 downto 0) := "00";  -- Addition operation
    
    -- Output signals
    signal result      : unsigned(15 downto 0);
    signal flag_zero   : std_logic;
    signal flag_neg    : std_logic;
    signal flag_carry  : std_logic;
    
    -- Simulation control
    signal finished    : std_logic := '0';

begin
    -- Instantiate the Unit Under Test (UUT)
    uut: ula_acc_bank port map(
        clk         => clk,
        rst         => rst,
        bank_wr_en  => bank_wr_en,
        reg_code    => reg_code,
        bank_data_in => bank_data_in,
        acc_wr_en   => acc_wr_en,
        selec_op    => selec_op,
        result      => result,
        flag_zero   => flag_zero,
        flag_neg    => flag_neg,
        flag_carry  => flag_carry
    );

    -- Clock process
    clk_process: process
    begin
        while finished /= '1' loop
            clk <= '0';
            wait for clk_period/2;
            clk <= '1';
            wait for clk_period/2;
        end loop;
        wait;
    end process;

    -- Stimulus process
    stim_proc: process
    begin
        -- Hold reset state for 100 ns
        rst <= '1';
        wait for 200 ns;
        rst <= '0';
        wait for clk_period;
        
        -- Test 1: Write vulae 10 to register 0
        bank_data_in <= to_unsigned(10, 16);
        reg_code <= "000";
        bank_wr_en <= '1';
        wait for clk_period;
        bank_wr_en <= '0';
        
        -- Test 2: Write vulae 20 to register 1
        bank_data_in <= to_unsigned(20, 16);
        reg_code <= "001";
        bank_wr_en <= '1';
        wait for clk_period;
        bank_wr_en <= '0';
        
        -- Test 3: Load vulae from register 0 (10) to accumulator through ula
        reg_code <= "000";  -- Select register 0
        selec_op <= "00";   -- Addition
        acc_wr_en <= '1';   -- Enable accumulator write
        wait for clk_period;
        acc_wr_en <= '0';
        
        -- Test 4: Add register 1 (20) to accumulator (10)
        reg_code <= "001";  -- Select register 1
        selec_op <= "00";   -- Addition
        acc_wr_en <= '1';   -- Enable accumulator write
        wait for clk_period;
        acc_wr_en <= '0';
        -- Accumulator should now contain 30 (10+20)
        
        -- Test 5: Subtract register 0 (10) from accumulator (30)
        reg_code <= "000";  -- Select register 0
        selec_op <= "01";   -- Subtraction
        acc_wr_en <= '1';   -- Enable accumulator write
        wait for clk_period;
        acc_wr_en <= '0';
        -- Accumulator should now contain 20 (30-10)
        
        -- Test 6: OR operation with register 1 (20)
        reg_code <= "001";  -- Select register 1
        selec_op <= "10";   -- OR operation
        acc_wr_en <= '1';   -- Enable accumulator write
        wait for clk_period;
        acc_wr_en <= '0';
        -- Accumulator should now contain 20 OR 20 = 20
        
        -- Test 7: Write a negative vulae to register 2 and test flags
        bank_data_in <= to_unsigned(65535, 16);  -- -1 in 2's complement
        reg_code <= "010";
        bank_wr_en <= '1';
        wait for clk_period;
        bank_wr_en <= '0';
        
        -- Test 8: Add negative vulae to accumulator to check negative flag
        reg_code <= "010";  -- Select register 2
        selec_op <= "00";   -- Addition
        acc_wr_en <= '1';   -- Enable accumulator write
        wait for clk_period;
        acc_wr_en <= '0';
        
        -- Test 9: Write big vulaes to test carry flag
        bank_data_in <= to_unsigned(65000, 16);
        reg_code <= "011";
        bank_wr_en <= '1';
        wait for clk_period;
        bank_wr_en <= '0';
        
        -- Test 10: Reset accumulator to 0
        rst <= '1';
        wait for clk_period;
        rst <= '0';
        
        -- Test 11: Add register 3 (65000) to accumulator (0)
        reg_code <= "011";
        selec_op <= "00";   -- Addition
        acc_wr_en <= '1';
        wait for clk_period;
        acc_wr_en <= '0';
        
        -- Test 12: Add register 3 again (65000) to test carry flag
        reg_code <= "011";
        selec_op <= "00";   -- Addition
        acc_wr_en <= '1';
        wait for clk_period;
        acc_wr_en <= '0';
        -- Should generate carry flag
        
        -- End of test
        wait for 300 ns;
        finished <= '1';
        wait;
    end process;

end architecture;

ULA_ACC_BANK/ula_acc_bank_tb.vcd
$date
  Wed May 21 18:55:16 2025
$end
$version
  GHDL v0
$end
$timescale
  1 fs
$end
$scope module standard $end
$upscope $end
$scope module std_logic_1164 $end
$upscope $end
$scope module numeric_std $end
$upscope $end
$scope module ula_acc_bank_tb $end
$var reg 1 ! clk $end
$var reg 1 " rst $end
$var reg 1 # bank_wr_en $end
$var reg 3 $ reg_code[2:0] $end
$var reg 16 % bank_data_in[15:0] $end
$var reg 1 & acc_wr_en $end
$var reg 2 ' selec_op[1:0] $end
$var reg 16 ( result[15:0] $end
$var reg 1 ) flag_zero $end
$var reg 1 * flag_neg $end
$var reg 1 + flag_carry $end
$var reg 1 , finished $end
$scope module uut $end
$var reg 1 - clk $end
$var reg 1 . rst $end
$var reg 1 / bank_wr_en $end
$var reg 3 0 reg_code[2:0] $end
$var reg 16 1 bank_data_in[15:0] $end
$var reg 1 2 acc_wr_en $end
$var reg 2 3 selec_op[1:0] $end
$var reg 16 4 result[15:0] $end
$var reg 1 5 flag_zero $end
$var reg 1 6 flag_neg $end
$var reg 1 7 flag_carry $end
$var reg 16 8 bank_data_out[15:0] $end
$var reg 16 9 acc_data_out[15:0] $end
$var reg 16 : ula_result[15:0] $end
$scope module bank $end
$var reg 16 ; data_in[15:0] $end
$var reg 1 < clk $end
$var reg 1 = wr_en $end
$var reg 3 > reg_code[2:0] $end
$var reg 1 ? rst $end
$var reg 16 @ data_out[15:0] $end
$var reg 16 A data_out_0_s[15:0] $end
$var reg 16 B data_out_1_s[15:0] $end
$var reg 16 C data_out_2_s[15:0] $end
$var reg 16 D data_out_3_s[15:0] $end
$var reg 16 E data_out_4_s[15:0] $end
$var reg 16 F data_out_5_s[15:0] $end
$var reg 1 G wr_en_0_s $end
$var reg 1 H wr_en_1_s $end
$var reg 1 I wr_en_2_s $end
$var reg 1 J wr_en_3_s $end
$var reg 1 K wr_en_4_s $end
$var reg 1 L wr_en_5_s $end
$scope module reg0 $end
$var reg 1 M clk $end
$var reg 1 N rst $end
$var reg 1 O wr_en $end
$var reg 16 P data_in[15:0] $end
$var reg 16 Q data_out[15:0] $end
$var reg 16 R registro[15:0] $end
$upscope $end
$scope module reg1 $end
$var reg 1 S clk $end
$var reg 1 T rst $end
$var reg 1 U wr_en $end
$var reg 16 V data_in[15:0] $end
$var reg 16 W data_out[15:0] $end
$var reg 16 X registro[15:0] $end
$upscope $end
$scope module reg2 $end
$var reg 1 Y clk $end
$var reg 1 Z rst $end
$var reg 1 [ wr_en $end
$var reg 16 \ data_in[15:0] $end
$var reg 16 ] data_out[15:0] $end
$var reg 16 ^ registro[15:0] $end
$upscope $end
$scope module reg3 $end
$var reg 1 _ clk $end
$var reg 1 ` rst $end
$var reg 1 a wr_en $end
$var reg 16 b data_in[15:0] $end
$var reg 16 c data_out[15:0] $end
$var reg 16 d registro[15:0] $end
$upscope $end
$scope module reg4 $end
$var reg 1 e clk $end
$var reg 1 f rst $end
$var reg 1 g wr_en $end
$var reg 16 h data_in[15:0] $end
$var reg 16 i data_out[15:0] $end
$var reg 16 j registro[15:0] $end
$upscope $end
$scope module reg5 $end
$var reg 1 k clk $end
$var reg 1 l rst $end
$var reg 1 m wr_en $end
$var reg 16 n data_in[15:0] $end
$var reg 16 o data_out[15:0] $end
$var reg 16 p registro[15:0] $end
$upscope $end
$upscope $end
$scope module acc $end
$var reg 1 q clk $end
$var reg 1 r rst $end
$var reg 1 s wr_en $end
$var reg 16 t data_in[15:0] $end
$var reg 16 u data_out[15:0] $end
$var reg 16 v data[15:0] $end
$upscope $end
$scope module ula_comp $end
$var reg 16 w entrada_a[15:0] $end
$var reg 16 x entrada_b[15:0] $end
$var reg 2 y selec_op[1:0] $end
$var reg 16 z resultado[15:0] $end
$var reg 1 { flag_zero $end
$var reg 1 | flag_neg $end
$var reg 1 } flag_carry $end
$var reg 16 !" resultado_temp[15:0] $end
$var reg 1 "" carry_temp $end
$var reg 17 #" soma_temp[16:0] $end
$upscope $end
$upscope $end
$upscope $end
$enddefinitions $end
#0
0!
1"
0#
b000 $
b0000000000000000 %
0&
b00 '
b0000000000000000 (
1)
0*
0+
0,
0-
1.
0/
b000 0
b0000000000000000 1
02
b00 3
b0000000000000000 4
15
06
07
b0000000000000000 8
b0000000000000000 9
b0000000000000000 :
b0000000000000000 ;
0<
0=
b000 >
1?
b0000000000000000 @
b0000000000000000 A
b0000000000000000 B
b0000000000000000 C
b0000000000000000 D
b0000000000000000 E
b0000000000000000 F
0G
0H
0I
0J
0K
0L
0M
1N
0O
b0000000000000000 P
b0000000000000000 Q
b0000000000000000 R
0S
1T
0U
b0000000000000000 V
b0000000000000000 W
b0000000000000000 X
0Y
1Z
0[
b0000000000000000 \
b0000000000000000 ]
b0000000000000000 ^
0_
1`
0a
b0000000000000000 b
b0000000000000000 c
b0000000000000000 d
0e
1f
0g
b0000000000000000 h
b0000000000000000 i
b0000000000000000 j
0k
1l
0m
b0000000000000000 n
b0000000000000000 o
b0000000000000000 p
0q
1r
0s
b0000000000000000 t
b0000000000000000 u
b0000000000000000 v
b0000000000000000 w
b0000000000000000 x
b00 y
b0000000000000000 z
1{
0|
0}
b0000000000000000 !"
0""
b00000000000000000 #"
#50000000
1!
1-
1<
1M
1S
1Y
1_
1e
1k
1q
#100000000
0!
0-
0<
0M
0S
0Y
0_
0e
0k
0q
#150000000
1!
1-
1<
1M
1S
1Y
1_
1e
1k
1q
#200000000
0!
0"
0-
0.
0<
0?
0M
0N
0S
0T
0Y
0Z
0_
0`
0e
0f
0k
0l
0q
0r
#250000000
1!
1-
1<
1M
1S
1Y
1_
1e
1k
1q
#300000000
0!
1#
b0000000000001010 %
0-
1/
b0000000000001010 1
b0000000000001010 ;
0<
1=
1G
0M
1O
b0000000000001010 P
0S
b0000000000001010 V
0Y
b0000000000001010 \
0_
b0000000000001010 b
0e
b0000000000001010 h
0k
b0000000000001010 n
0q
#350000000
1!
b0000000000001010 (
0)
1-
b0000000000001010 4
05
b0000000000001010 8
b0000000000001010 :
1<
b0000000000001010 @
b0000000000001010 A
1M
b0000000000001010 Q
b0000000000001010 R
1S
1Y
1_
1e
1k
1q
b0000000000001010 t
b0000000000001010 x
b0000000000001010 z
0{
b0000000000001010 !"
b00000000000001010 #"
#400000000
0!
b001 $
b0000000000010100 %
b0000000000000000 (
1)
0-
b001 0
b0000000000010100 1
b0000000000000000 4
15
b0000000000000000 8
b0000000000000000 :
b0000000000010100 ;
0<
b001 >
b0000000000000000 @
0G
1H
0M
0O
b0000000000010100 P
0S
1U
b0000000000010100 V
0Y
b0000000000010100 \
0_
b0000000000010100 b
0e
b0000000000010100 h
0k
b0000000000010100 n
0q
b0000000000000000 t
b0000000000000000 x
b0000000000000000 z
1{
b0000000000000000 !"
b00000000000000000 #"
#450000000
1!
b0000000000010100 (
0)
1-
b0000000000010100 4
05
b0000000000010100 8
b0000000000010100 :
1<
b0000000000010100 @
b0000000000010100 B
1M
1S
b0000000000010100 W
b0000000000010100 X
1Y
1_
1e
1k
1q
b0000000000010100 t
b0000000000010100 x
b0000000000010100 z
0{
b0000000000010100 !"
b00000000000010100 #"
#500000000
0!
0#
b000 $
1&
b0000000000001010 (
0-
0/
b000 0
12
b0000000000001010 4
b0000000000001010 8
b0000000000001010 :
0<
0=
b000 >
b0000000000001010 @
0H
0M
0S
0U
0Y
0_
0e
0k
0q
1s
b0000000000001010 t
b0000000000001010 x
b0000000000001010 z
b0000000000001010 !"
b00000000000001010 #"
#550000000
1!
b0000000000010100 (
1-
b0000000000010100 4
b0000000000001010 9
b0000000000010100 :
1<
1M
1S
1Y
1_
1e
1k
1q
b0000000000010100 t
b0000000000001010 u
b0000000000001010 v
b0000000000001010 w
b0000000000010100 z
b0000000000010100 !"
b00000000000010100 #"
#600000000
0!
b001 $
b0000000000011110 (
0-
b001 0
b0000000000011110 4
b0000000000010100 8
b0000000000011110 :
0<
b001 >
b0000000000010100 @
0M
0S
0Y
0_
0e
0k
0q
b0000000000011110 t
b0000000000010100 x
b0000000000011110 z
b0000000000011110 !"
b00000000000011110 #"
#650000000
1!
b0000000000110010 (
1-
b0000000000110010 4
b0000000000011110 9
b0000000000110010 :
1<
1M
1S
1Y
1_
1e
1k
1q
b0000000000110010 t
b0000000000011110 u
b0000000000011110 v
b0000000000011110 w
b0000000000110010 z
b0000000000110010 !"
b00000000000110010 #"
#700000000
0!
b000 $
b01 '
b0000000000010100 (
1+
0-
b000 0
b01 3
b0000000000010100 4
17
b0000000000001010 8
b0000000000010100 :
0<
b000 >
b0000000000001010 @
0M
0S
0Y
0_
0e
0k
0q
b0000000000010100 t
b0000000000001010 x
b01 y
b0000000000010100 z
1}
b0000000000010100 !"
1""
b00000000000010100 #"
#750000000
1!
b0000000000001010 (
1-
b0000000000001010 4
b0000000000010100 9
b0000000000001010 :
1<
1M
1S
1Y
1_
1e
1k
1q
b0000000000001010 t
b0000000000010100 u
b0000000000010100 v
b0000000000010100 w
b0000000000001010 z
b0000000000001010 !"
b00000000000001010 #"
#800000000
0!
b001 $
b10 '
b0000000000010100 (
0+
0-
b001 0
b10 3
b0000000000010100 4
07
b0000000000010100 8
b0000000000010100 :
0<
b001 >
b0000000000010100 @
0M
0S
0Y
0_
0e
0k
0q
b0000000000010100 t
b0000000000010100 x
b10 y
b0000000000010100 z
0}
b0000000000010100 !"
0""
b00000000000010100 #"
#850000000
1!
1-
1<
1M
1S
1Y
1_
1e
1k
1q
#900000000
0!
1#
b010 $
b1111111111111111 %
0&
0-
1/
b010 0
b1111111111111111 1
02
b0000000000000000 8
b1111111111111111 ;
0<
1=
b010 >
b0000000000000000 @
1I
0M
b1111111111111111 P
0S
b1111111111111111 V
0Y
1[
b1111111111111111 \
0_
b1111111111111111 b
0e
b1111111111111111 h
0k
b1111111111111111 n
0q
0s
b0000000000000000 x
#950000000
1!
b1111111111111111 (
1*
1-
b1111111111111111 4
16
b1111111111111111 8
b1111111111111111 :
1<
b1111111111111111 @
b1111111111111111 C
1M
1S
1Y
b1111111111111111 ]
b1111111111111111 ^
1_
1e
1k
1q
b1111111111111111 t
b1111111111111111 x
b1111111111111111 z
1|
b1111111111111111 !"
b01111111111111111 #"
#1000000000
0!
0#
1&
b00 '
b0000000000010011 (
0*
1+
0-
0/
12
b00 3
b0000000000010011 4
06
17
b0000000000010011 :
0<
0=
0I
0M
0S
0Y
0[
0_
0e
0k
0q
1s
b0000000000010011 t
b00 y
b0000000000010011 z
0|
1}
b0000000000010011 !"
1""
b10000000000010011 #"
#1050000000
1!
b0000000000010010 (
1-
b0000000000010010 4
b0000000000010011 9
b0000000000010010 :
1<
1M
1S
1Y
1_
1e
1k
1q
b0000000000010010 t
b0000000000010011 u
b0000000000010011 v
b0000000000010011 w
b0000000000010010 z
b0000000000010010 !"
b10000000000010010 #"
#1100000000
0!
1#
b011 $
b1111110111101000 %
0&
b0000000000010011 (
0+
0-
1/
b011 0
b1111110111101000 1
02
b0000000000010011 4
07
b0000000000000000 8
b0000000000010011 :
b1111110111101000 ;
0<
1=
b011 >
b0000000000000000 @
1J
0M
b1111110111101000 P
0S
b1111110111101000 V
0Y
b1111110111101000 \
0_
1a
b1111110111101000 b
0e
b1111110111101000 h
0k
b1111110111101000 n
0q
0s
b0000000000010011 t
b0000000000000000 x
b0000000000010011 z
0}
b0000000000010011 !"
0""
b00000000000010011 #"
#1150000000
1!
b1111110111111011 (
1*
1-
b1111110111111011 4
16
b1111110111101000 8
b1111110111111011 :
1<
b1111110111101000 @
b1111110111101000 D
1M
1S
1Y
1_
b1111110111101000 c
b1111110111101000 d
1e
1k
1q
b1111110111111011 t
b1111110111101000 x
b1111110111111011 z
1|
b1111110111111011 !"
b01111110111111011 #"
#1200000000
0!
1"
0#
b0000000000000000 (
1)
0*
0-
1.
0/
b0000000000000000 4
15
06
b0000000000000000 8
b0000000000000000 9
b0000000000000000 :
0<
0=
1?
b0000000000000000 @
b0000000000000000 A
b0000000000000000 B
b0000000000000000 C
b0000000000000000 D
0J
0M
1N
b0000000000000000 Q
b0000000000000000 R
0S
1T
b0000000000000000 W
b0000000000000000 X
0Y
1Z
b0000000000000000 ]
b0000000000000000 ^
0_
1`
0a
b0000000000000000 c
b0000000000000000 d
0e
1f
0k
1l
0q
1r
b0000000000000000 t
b0000000000000000 u
b0000000000000000 v
b0000000000000000 w
b0000000000000000 x
b0000000000000000 z
1{
0|
b0000000000000000 !"
b00000000000000000 #"
#1250000000
1!
1-
1<
1M
1S
1Y
1_
1e
1k
1q
#1300000000
0!
0"
1&
0-
0.
12
0<
0?
0M
0N
0S
0T
0Y
0Z
0_
0`
0e
0f
0k
0l
0q
0r
1s
#1350000000
1!
1-
1<
1M
1S
1Y
1_
1e
1k
1q
#1400000000
0!
0-
0<
0M
0S
0Y
0_
0e
0k
0q
#1450000000
1!
1-
1<
1M
1S
1Y
1_
1e
1k
1q
#1500000000
0!
0&
0-
02
0<
0M
0S
0Y
0_
0e
0k
0q
0s
#1550000000
1!
1-
1<
1M
1S
1Y
1_
1e
1k
1q
#1600000000
0!
0-
0<
0M
0S
0Y
0_
0e
0k
0q
#1650000000
1!
1-
1<
1M
1S
1Y
1_
1e
1k
1q
#1700000000
0!
0-
0<
0M
0S
0Y
0_
0e
0k
0q
#1750000000
1!
1-
1<
1M
1S
1Y
1_
1e
1k
1q
#1800000000
0!
1,
0-
0<
0M
0S
0Y
0_
0e
0k
0q
