reg16bits.vhd
library ieee;
use ieee.std_logic_1164.all;
use ieee.numeric_std.all;

entity reg16bits is
   port( clk      : in std_logic;
         rst      : in std_logic;
         wr_en    : in std_logic;
         data_in  : in unsigned(15 downto 0);
         data_out : out unsigned(15 downto 0)
   );
end entity;

architecture a_reg16bits of reg16bits is
   signal registro: unsigned(15 downto 0);
begin
   process(clk,rst,wr_en)  -- acionado se houver mudança em clk, rst ou wr_en
   begin
      if rst='1' then
         registro <= "0000000000000000";
      elsif wr_en='1' then
         if rising_edge(clk) then
            registro <= data_in;
         end if;
      end if;
   end process;

   data_out <= registro;  -- conexao direta, fora do processo
end architecture;

register_bank.vhd
library ieee;
use ieee.std_logic_1164.all;
use ieee.numeric_std.all;

entity register_bank is
    port(
        data_in   : in unsigned(15 downto 0);
        clk       : in std_logic;
        wr_en     : in std_logic;
        reg_code  : in unsigned(2 downto 0);
        rst       : in std_logic;
        data_out  : out unsigned(15 downto 0)
    );
end entity register_bank;

architecture a_register_bank of register_bank is
  component reg16bits is
    port (
        clk      : in std_logic;
        rst      : in std_logic;
        wr_en    : in std_logic;
        data_in  : in unsigned(15 downto 0);
        data_out : out unsigned(15 downto 0)
    );
  end component;

  signal data_out_0_s,data_out_1_s,data_out_2_s : unsigned(15 downto 0) := (others => '0');
  signal data_out_3_s,data_out_4_s,data_out_5_s : unsigned(15 downto 0) := (others => '0');

  signal wr_en_0_s,wr_en_1_s,wr_en_2_s : std_logic := '0';
  signal wr_en_3_s,wr_en_4_s,wr_en_5_s : std_logic := '0';

  begin

    --WRITE ENABLE
    wr_en_0_s <= '1' when wr_en = '1' and reg_code = "000" else '0';
    wr_en_1_s <= '1' when wr_en = '1' and reg_code = "001" else '0';
    wr_en_2_s <= '1' when wr_en = '1' and reg_code = "010" else '0';
    wr_en_3_s <= '1' when wr_en = '1' and reg_code = "011" else '0';
    wr_en_4_s <= '1' when wr_en = '1' and reg_code = "100" else '0';
    wr_en_5_s <= '1' when wr_en = '1' and reg_code = "101" else '0';


    --REGISTER DEFINITION
    reg0: reg16bits port map(clk,rst,wr_en_0_s,data_in,data_out_0_s);
    reg1: reg16bits port map(clk,rst,wr_en_1_s,data_in,data_out_1_s);
    reg2: reg16bits port map(clk,rst,wr_en_2_s,data_in,data_out_2_s);
    reg3: reg16bits port map(clk,rst,wr_en_3_s,data_in,data_out_3_s);
    reg4: reg16bits port map(clk,rst,wr_en_4_s,data_in,data_out_4_s);
    reg5: reg16bits port map(clk,rst,wr_en_5_s,data_in,data_out_5_s);

    data_out <= data_out_0_s when reg_code = "000" else
                data_out_1_s when reg_code = "001" else
                data_out_2_s when reg_code = "010" else
                data_out_3_s when reg_code = "011" else
                data_out_4_s when reg_code = "100" else
                data_out_5_s when reg_code = "101" else
                "0000000000000000";

end architecture a_register_bank;

REGISTER_BANK/register_bank_tb.vhd
library ieee;
use ieee.std_logic_1164.all;
use ieee.numeric_std.all;

entity register_bank_tb is
end entity;

architecture a_register_bank_tb of register_bank_tb is
  component register_bank is
    port(
        data_in   : in unsigned(15 downto 0);
        clk       : in std_logic;
        wr_en     : in std_logic;
        reg_code  : in unsigned(2 downto 0);
        rst       : in std_logic;
        data_out  : out unsigned(15 downto 0)
    );
  end component;

  -- Sinais para conectar ao componente
  constant period_time  : time := 100 ns;
  signal    finished,clk_s,wr_en_s    : std_logic := '0';
  signal    rst_s : std_logic := '1'; -- Inicializa reset como ativo
  signal    data_in_s,data_out_s : unsigned(15 downto 0) := (others => '0');
  signal    reg_code_s : unsigned(2 downto 0) := (others => '0');

  -- Sinais para melhor visualização
  signal teste_atual : integer := 0; -- Sinal para identificar fase de teste atual

  -- Instanciação do componente
begin
  UTT: register_bank port map (
    data_in   => data_in_s,
    clk       => clk_s,
    wr_en     => wr_en_s,
    reg_code  => reg_code_s,
    rst       => rst_s,
    data_out  => data_out_s
  );


  -- Tempo total da simulação
  sim_time_proc:process
  begin
    wait for 20 us; -- Tempo suficiente para todos os testes
    finished <= '1';
    wait;
  end process;

  -- Geração de clock
  clk_proc:process
  begin
    while finished /= '1' loop
      clk_s <= '0';
      wait for 50 ns;
      clk_s <= '1';
      wait for 50 ns;
    end loop;
    wait;
  end process clk_proc;

  -- Processo de teste principal
  test_proc: process
  begin
    report "Testbench iniciado" severity note;
    
    -- Inicialização
    wr_en_s <= '0';
    data_in_s <= (others => '0');
    reg_code_s <= "000";
    teste_atual <= 0;
    
     -- Reset inicial
    rst_s <= '1'; -- Reset ativo
    wait for 200 ns;
    rst_s <= '0'; -- Desativa reset
    
    -- Espera um pouco para garantir
    wait for 100 ns;
    teste_atual <= 1; -- Indicador para GTKWave
    report "Reset completo, iniciando testes" severity note;
    
    -- Teste 1: Escreve nos registradores
    wr_en_s <= '1';

    -- Escreve 1 no registrador 0
    data_in_s <= x"0001";
    reg_code_s <= "000";
    wait for period_time;

    -- Escreve 2 no registrador 1
    data_in_s <= x"0002";
    reg_code_s <= "001";
    wait for period_time;

    -- Escreve 3 no registrador 2
    data_in_s <= x"0003";
    reg_code_s <= "010";
    wait for period_time;

    -- Escreve 4 no registrador 3
    data_in_s <= x"0004";
    reg_code_s <= "011";
    wait for period_time;

    -- Escreve 5 no registrador 4
    data_in_s <= x"0005";
    reg_code_s <= "100";
    wait for period_time;

    -- Escreve 6 no registrador 5
    data_in_s <= x"0006";
    reg_code_s <= "101";
    wait for period_time;
    
    report "Escrita em registradores completa" severity note;
    teste_atual <= 2; -- Indicador para GTKWave

    -- Teste 2: Lê todos os registradores
    wr_en_s <= '0';
    
    -- Lê registrador 0, deve mostrar 1
    reg_code_s <= "000";
    wait for period_time;
    assert data_out_s = x"0001" report "Erro na leitura do registrador 0" severity error;
    
    -- Lê registrador 1, deve mostrar 2
    reg_code_s <= "001";
    wait for period_time;
    assert data_out_s = x"0002" report "Erro na leitura do registrador 1" severity error;
    
    -- Lê registrador 2, deve mostrar 3
    reg_code_s <= "010";
    wait for period_time;
    assert data_out_s = x"0003" report "Erro na leitura do registrador 2" severity error;
    
    -- Lê registrador 3, deve mostrar 4
    reg_code_s <= "011";
    wait for period_time;
    assert data_out_s = x"0004" report "Erro na leitura do registrador 3" severity error;
    
    -- Lê registrador 4, deve mostrar 5
    reg_code_s <= "100";
    wait for period_time;
    assert data_out_s = x"0005" report "Erro na leitura do registrador 4" severity error;
    
    -- Lê registrador 5, deve mostrar 6
    reg_code_s <= "101";
    wait for period_time;
    assert data_out_s = x"0006" report "Erro na leitura do registrador 5" severity error;
    
    report "Leitura de registradores completa" severity note;
    teste_atual <= 3; -- Indicador para GTKWave

    -- Teste 3: Tenta escrever com wr_en desligado
    data_in_s <= x"FFFF"; -- Valor diferente para confirmar que não vai mudar
    
    -- Tenta escrever FFFF no registrador 0
    reg_code_s <= "000";
    wait for period_time;
    
    -- Lê registrador 0 novamente, deve continuar 1
    reg_code_s <= "000";
    wait for period_time;
    assert data_out_s = x"0001" report "Escrita indevida com wr_en=0" severity error;
    
    report "Teste de escrita bloqueada completo" severity note;
    teste_atual <= 4; -- Indicador para GTKWave

    -- Teste 4: Escreve com wr_en ligado novamente
    wr_en_s <= '1';
    
    -- Escreve FF no registrador 2
    data_in_s <= x"00FF";
    reg_code_s <= "010";
    wait for period_time;
    
    -- Lê registrador 2, deve mostrar FF
    wr_en_s <= '0';
    reg_code_s <= "010";
    wait for period_time;
    assert data_out_s = x"00FF" report "Erro na escrita do registrador 2" severity error;

    -- Lê todos os registradores novamente para confirmar que só o 2 mudou
    reg_code_s <= "000"; -- Deve mostrar 1
    wait for period_time;
    assert data_out_s = x"0001" report "Registrador 0 alterado indevidamente" severity error;
    
    reg_code_s <= "001"; -- Deve mostrar 2
    wait for period_time;
    assert data_out_s = x"0002" report "Registrador 1 alterado indevidamente" severity error;
    
    reg_code_s <= "010"; -- Deve mostrar FF
    wait for period_time;
    assert data_out_s = x"00FF" report "Registrador 2 não foi alterado corretamente" severity error;
    
    reg_code_s <= "011"; -- Deve mostrar 4
    wait for period_time;
    assert data_out_s = x"0004" report "Registrador 3 alterado indevidamente" severity error;
    
    reg_code_s <= "100"; -- Deve mostrar 5
    wait for period_time;
    assert data_out_s = x"0005" report "Registrador 4 alterado indevidamente" severity error;
    
    reg_code_s <= "101"; -- Deve mostrar 6
    wait for period_time;
    assert data_out_s = x"0006" report "Registrador 5 alterado indevidamente" severity error;
    
    report "Teste de escrita seletiva completo" severity note;
    teste_atual <= 5; -- Indicador para GTKWave

    -- Teste 5: Verificar comportamento com reset
    rst_s <= '1';
    wait for period_time*2; -- Espera 2 ciclos para garantir que o reset seja aplicado
    rst_s <= '0';
    wait for period_time; -- Espera mais um ciclo após desativar o reset
    
    -- Lê todos os registradores novamente, devem estar zerados
    reg_code_s <= "000"; -- Deve mostrar 0
    wait for period_time;
    assert data_out_s = x"0000" report "Reset falhou para registrador 0" severity error;
    
    reg_code_s <= "001"; -- Deve mostrar 0
    wait for period_time;
    assert data_out_s = x"0000" report "Reset falhou para registrador 1" severity error;
    
    reg_code_s <= "010"; -- Deve mostrar 0
    wait for period_time;
    assert data_out_s = x"0000" report "Reset falhou para registrador 2" severity error;
    
    reg_code_s <= "011"; -- Deve mostrar 0
    wait for period_time;
    assert data_out_s = x"0000" report "Reset falhou para registrador 3" severity error;
    
    reg_code_s <= "100"; -- Deve mostrar 0
    wait for period_time;
    assert data_out_s = x"0000" report "Reset falhou para registrador 4" severity error;
    
    reg_code_s <= "101"; -- Deve mostrar 0
    wait for period_time;
    assert data_out_s = x"0000" report "Reset falhou para registrador 5" severity error;
    
    report "Teste de reset completo" severity note;
    teste_atual <= 6; -- Teste adicional
    
    -- Teste adicional: Reescreve nos registradores após reset
    wr_en_s <= '1';
    
    -- Escreve 42 no registrador 3
    data_in_s <= x"002A"; -- 42 em hex
    reg_code_s <= "011";
    wait for period_time;
    
    -- Lê registrador 3
    wr_en_s <= '0';
    wait for period_time;
    assert data_out_s = x"002A" report "Erro na escrita após reset" severity error;
    
    report "Testbench concluido com sucesso" severity note;
    teste_atual <= 7; -- Fim dos testes
    
    wait; -- Finaliza o processo de teste
  end process test_proc;
end architecture;

register_bank_tb.vcd
$date
  Wed May 21 18:35:10 2025
$end
$version
  GHDL v0
$end
$timescale
  1 fs
$end
$scope module standard $end
$upscope $end
$scope module std_logic_1164 $end
$upscope $end
$scope module numeric_std $end
$upscope $end
$scope module register_bank_tb $end
$var reg 1 ! finished $end
$var reg 1 " clk_s $end
$var reg 1 # wr_en_s $end
$var reg 1 $ rst_s $end
$var reg 16 % data_in_s[15:0] $end
$var reg 16 & data_out_s[15:0] $end
$var reg 3 ' reg_code_s[2:0] $end
$var integer 32 ( teste_atual $end
$scope module utt $end
$var reg 16 ) data_in[15:0] $end
$var reg 1 * clk $end
$var reg 1 + wr_en $end
$var reg 3 , reg_code[2:0] $end
$var reg 1 - rst $end
$var reg 16 . data_out[15:0] $end
$var reg 16 / data_out_0_s[15:0] $end
$var reg 16 0 data_out_1_s[15:0] $end
$var reg 16 1 data_out_2_s[15:0] $end
$var reg 16 2 data_out_3_s[15:0] $end
$var reg 16 3 data_out_4_s[15:0] $end
$var reg 16 4 data_out_5_s[15:0] $end
$var reg 1 5 wr_en_0_s $end
$var reg 1 6 wr_en_1_s $end
$var reg 1 7 wr_en_2_s $end
$var reg 1 8 wr_en_3_s $end
$var reg 1 9 wr_en_4_s $end
$var reg 1 : wr_en_5_s $end
$scope module reg0 $end
$var reg 1 ; clk $end
$var reg 1 < rst $end
$var reg 1 = wr_en $end
$var reg 16 > data_in[15:0] $end
$var reg 16 ? data_out[15:0] $end
$var reg 16 @ registro[15:0] $end
$upscope $end
$scope module reg1 $end
$var reg 1 A clk $end
$var reg 1 B rst $end
$var reg 1 C wr_en $end
$var reg 16 D data_in[15:0] $end
$var reg 16 E data_out[15:0] $end
$var reg 16 F registro[15:0] $end
$upscope $end
$scope module reg2 $end
$var reg 1 G clk $end
$var reg 1 H rst $end
$var reg 1 I wr_en $end
$var reg 16 J data_in[15:0] $end
$var reg 16 K data_out[15:0] $end
$var reg 16 L registro[15:0] $end
$upscope $end
$scope module reg3 $end
$var reg 1 M clk $end
$var reg 1 N rst $end
$var reg 1 O wr_en $end
$var reg 16 P data_in[15:0] $end
$var reg 16 Q data_out[15:0] $end
$var reg 16 R registro[15:0] $end
$upscope $end
$scope module reg4 $end
$var reg 1 S clk $end
$var reg 1 T rst $end
$var reg 1 U wr_en $end
$var reg 16 V data_in[15:0] $end
$var reg 16 W data_out[15:0] $end
$var reg 16 X registro[15:0] $end
$upscope $end
$scope module reg5 $end
$var reg 1 Y clk $end
$var reg 1 Z rst $end
$var reg 1 [ wr_en $end
$var reg 16 \ data_in[15:0] $end
$var reg 16 ] data_out[15:0] $end
$var reg 16 ^ registro[15:0] $end
$upscope $end
$upscope $end
$upscope $end
$enddefinitions $end
#0
0!
0"
0#
1$
b0000000000000000 %
b0000000000000000 &
b000 '
b0 (
b0000000000000000 )
0*
0+
b000 ,
1-
b0000000000000000 .
b0000000000000000 /
b0000000000000000 0
b0000000000000000 1
b0000000000000000 2
b0000000000000000 3
b0000000000000000 4
05
06
07
08
09
0:
0;
1<
0=
b0000000000000000 >
b0000000000000000 ?
b0000000000000000 @
0A
1B
0C
b0000000000000000 D
b0000000000000000 E
b0000000000000000 F
0G
1H
0I
b0000000000000000 J
b0000000000000000 K
b0000000000000000 L
0M
1N
0O
b0000000000000000 P
b0000000000000000 Q
b0000000000000000 R
0S
1T
0U
b0000000000000000 V
b0000000000000000 W
b0000000000000000 X
0Y
1Z
0[
b0000000000000000 \
b0000000000000000 ]
b0000000000000000 ^
#50000000
1"
1*
1;
1A
1G
1M
1S
1Y
#100000000
0"
0*
0;
0A
0G
0M
0S
0Y
#150000000
1"
1*
1;
1A
1G
1M
1S
1Y
#200000000
0"
0$
0*
0-
0;
0<
0A
0B
0G
0H
0M
0N
0S
0T
0Y
0Z
#250000000
1"
1*
1;
1A
1G
1M
1S
1Y
#300000000
0"
1#
b0000000000000001 %
b1 (
b0000000000000001 )
0*
1+
15
0;
1=
b0000000000000001 >
0A
b0000000000000001 D
0G
b0000000000000001 J
0M
b0000000000000001 P
0S
b0000000000000001 V
0Y
b0000000000000001 \
#350000000
1"
b0000000000000001 &
1*
b0000000000000001 .
b0000000000000001 /
1;
b0000000000000001 ?
b0000000000000001 @
1A
1G
1M
1S
1Y
#400000000
0"
b0000000000000010 %
b0000000000000000 &
b001 '
b0000000000000010 )
0*
b001 ,
b0000000000000000 .
05
16
0;
0=
b0000000000000010 >
0A
1C
b0000000000000010 D
0G
b0000000000000010 J
0M
b0000000000000010 P
0S
b0000000000000010 V
0Y
b0000000000000010 \
#450000000
1"
b0000000000000010 &
1*
b0000000000000010 .
b0000000000000010 0
1;
1A
b0000000000000010 E
b0000000000000010 F
1G
1M
1S
1Y
#500000000
0"
b0000000000000011 %
b0000000000000000 &
b010 '
b0000000000000011 )
0*
b010 ,
b0000000000000000 .
06
17
0;
b0000000000000011 >
0A
0C
b0000000000000011 D
0G
1I
b0000000000000011 J
0M
b0000000000000011 P
0S
b0000000000000011 V
0Y
b0000000000000011 \
#550000000
1"
b0000000000000011 &
1*
b0000000000000011 .
b0000000000000011 1
1;
1A
1G
b0000000000000011 K
b0000000000000011 L
1M
1S
1Y
#600000000
0"
b0000000000000100 %
b0000000000000000 &
b011 '
b0000000000000100 )
0*
b011 ,
b0000000000000000 .
07
18
0;
b0000000000000100 >
0A
b0000000000000100 D
0G
0I
b0000000000000100 J
0M
1O
b0000000000000100 P
0S
b0000000000000100 V
0Y
b0000000000000100 \
#650000000
1"
b0000000000000100 &
1*
b0000000000000100 .
b0000000000000100 2
1;
1A
1G
1M
b0000000000000100 Q
b0000000000000100 R
1S
1Y
#700000000
0"
b0000000000000101 %
b0000000000000000 &
b100 '
b0000000000000101 )
0*
b100 ,
b0000000000000000 .
08
19
0;
b0000000000000101 >
0A
b0000000000000101 D
0G
b0000000000000101 J
0M
0O
b0000000000000101 P
0S
1U
b0000000000000101 V
0Y
b0000000000000101 \
#750000000
1"
b0000000000000101 &
1*
b0000000000000101 .
b0000000000000101 3
1;
1A
1G
1M
1S
b0000000000000101 W
b0000000000000101 X
1Y
#800000000
0"
b0000000000000110 %
b0000000000000000 &
b101 '
b0000000000000110 )
0*
b101 ,
b0000000000000000 .
09
1:
0;
b0000000000000110 >
0A
b0000000000000110 D
0G
b0000000000000110 J
0M
b0000000000000110 P
0S
0U
b0000000000000110 V
0Y
1[
b0000000000000110 \
#850000000
1"
b0000000000000110 &
1*
b0000000000000110 .
b0000000000000110 4
1;
1A
1G
1M
1S
1Y
b0000000000000110 ]
b0000000000000110 ^
#900000000
0"
0#
b0000000000000001 &
b000 '
b10 (
0*
0+
b000 ,
b0000000000000001 .
0:
0;
0A
0G
0M
0S
0Y
0[
#950000000
1"
1*
1;
1A
1G
1M
1S
1Y
#1000000000
0"
b0000000000000010 &
b001 '
0*
b001 ,
b0000000000000010 .
0;
0A
0G
0M
0S
0Y
#1050000000
1"
1*
1;
1A
1G
1M
1S
1Y
#1100000000
0"
b0000000000000011 &
b010 '
0*
b010 ,
b0000000000000011 .
0;
0A
0G
0M
0S
0Y
#1150000000
1"
1*
1;
1A
1G
1M
1S
1Y
#1200000000
0"
b0000000000000100 &
b011 '
0*
b011 ,
b0000000000000100 .
0;
0A
0G
0M
0S
0Y
#1250000000
1"
1*
1;
1A
1G
1M
1S
1Y
#1300000000
0"
b0000000000000101 &
b100 '
0*
b100 ,
b0000000000000101 .
0;
0A
0G
0M
0S
0Y
#1350000000
1"
1*
1;
1A
1G
1M
1S
1Y
#1400000000
0"
b0000000000000110 &
b101 '
0*
b101 ,
b0000000000000110 .
0;
0A
0G
0M
0S
0Y
#1450000000
1"
1*
1;
1A
1G
1M
1S
1Y
#1500000000
0"
b1111111111111111 %
b0000000000000001 &
b000 '
b11 (
b1111111111111111 )
0*
b000 ,
b0000000000000001 .
0;
b1111111111111111 >
0A
b1111111111111111 D
0G
b1111111111111111 J
0M
b1111111111111111 P
0S
b1111111111111111 V
0Y
b1111111111111111 \
#1550000000
1"
1*
1;
1A
1G
1M
1S
1Y
#1600000000
0"
0*
0;
0A
0G
0M
0S
0Y
#1650000000
1"
1*
1;
1A
1G
1M
1S
1Y
#1700000000
0"
1#
b0000000011111111 %
b0000000000000011 &
b010 '
b100 (
b0000000011111111 )
0*
1+
b010 ,
b0000000000000011 .
17
0;
b0000000011111111 >
0A
b0000000011111111 D
0G
1I
b0000000011111111 J
0M
b0000000011111111 P
0S
b0000000011111111 V
0Y
b0000000011111111 \
#1750000000
1"
b0000000011111111 &
1*
b0000000011111111 .
b0000000011111111 1
1;
1A
1G
b0000000011111111 K
b0000000011111111 L
1M
1S
1Y
#1800000000
0"
0#
0*
0+
07
0;
0A
0G
0I
0M
0S
0Y
#1850000000
1"
1*
1;
1A
1G
1M
1S
1Y
#1900000000
0"
b0000000000000001 &
b000 '
0*
b000 ,
b0000000000000001 .
0;
0A
0G
0M
0S
0Y
#1950000000
1"
1*
1;
1A
1G
1M
1S
1Y
#2000000000
0"
b0000000000000010 &
b001 '
0*
b001 ,
b0000000000000010 .
0;
0A
0G
0M
0S
0Y
#2050000000
1"
1*
1;
1A
1G
1M
1S
1Y
#2100000000
0"
b0000000011111111 &
b010 '
0*
b010 ,
b0000000011111111 .
0;
0A
0G
0M
0S
0Y
#2150000000
1"
1*
1;
1A
1G
1M
1S
1Y
#2200000000
0"
b0000000000000100 &
b011 '
0*
b011 ,
b0000000000000100 .
0;
0A
0G
0M
0S
0Y
#2250000000
1"
1*
1;
1A
1G
1M
1S
1Y
#2300000000
0"
b0000000000000101 &
b100 '
0*
b100 ,
b0000000000000101 .
0;
0A
0G
0M
0S
0Y
#2350000000
1"
1*
1;
1A
1G
1M
1S
1Y
#2400000000
0"
b0000000000000110 &
b101 '
0*
b101 ,
b0000000000000110 .
0;
0A
0G
0M
0S
0Y
#2450000000
1"
1*
1;
1A
1G
1M
1S
1Y
#2500000000
0"
1$
b0000000000000000 &
b101 (
0*
1-
b0000000000000000 .
b0000000000000000 /
b0000000000000000 0
b0000000000000000 1
b0000000000000000 2
b0000000000000000 3
b0000000000000000 4
0;
1<
b0000000000000000 ?
b0000000000000000 @
0A
1B
b0000000000000000 E
b0000000000000000 F
0G
1H
b0000000000000000 K
b0000000000000000 L
0M
1N
b0000000000000000 Q
b0000000000000000 R
0S
1T
b0000000000000000 W
b0000000000000000 X
0Y
1Z
b0000000000000000 ]
b0000000000000000 ^
#2550000000
1"
1*
1;
1A
1G
1M
1S
1Y
#2600000000
0"
0*
0;
0A
0G
0M
0S
0Y
#2650000000
1"
1*
1;
1A
1G
1M
1S
1Y
#2700000000
0"
0$
0*
0-
0;
0<
0A
0B
0G
0H
0M
0N
0S
0T
0Y
0Z
#2750000000
1"
1*
1;
1A
1G
1M
1S
1Y
#2800000000
0"
b000 '
0*
b000 ,
0;
0A
0G
0M
0S
0Y
#2850000000
1"
1*
1;
1A
1G
1M
1S
1Y
#2900000000
0"
b001 '
0*
b001 ,
0;
0A
0G
0M
0S
0Y
#2950000000
1"
1*
1;
1A
1G
1M
1S
1Y
#3000000000
0"
b010 '
0*
b010 ,
0;
0A
0G
0M
0S
0Y
#3050000000
1"
1*
1;
1A
1G
1M
1S
1Y
#3100000000
0"
b011 '
0*
b011 ,
0;
0A
0G
0M
0S
0Y
#3150000000
1"
1*
1;
1A
1G
1M
1S
1Y
#3200000000
0"
b100 '
0*
b100 ,
0;
0A
0G
0M
0S
0Y
#3250000000
1"
1*
1;
1A
1G
1M
1S
1Y
#3300000000
0"
b101 '
0*
b101 ,
0;
0A
0G
0M
0S
0Y
#3350000000
1"
1*
1;
1A
1G
1M
1S
1Y
#3400000000
0"
1#
b0000000000101010 %
b011 '
b110 (
b0000000000101010 )
0*
1+
b011 ,
18
0;
b0000000000101010 >
0A
b0000000000101010 D
0G
b0000000000101010 J
0M
1O
b0000000000101010 P
0S
b0000000000101010 V
0Y
b0000000000101010 \
#3450000000
1"
b0000000000101010 &
1*
b0000000000101010 .
b0000000000101010 2
1;
1A
1G
1M
b0000000000101010 Q
b0000000000101010 R
1S
1Y
#3500000000
0"
0#
0*
0+
08
0;
0A
0G
0M
0O
0S
0Y
#3550000000
1"
1*
1;
1A
1G
1M
1S
1Y
#3600000000
0"
b111 (
0*
0;
0A
0G
0M
0S
0Y
